tool_parse/__init__.py
tool_parse/_registry.py
tool_parse/_tool.py
tool_parse/_types.py
tool_parse/compile.py
tool_parse/exceptions.py
tool_parse/integrations/__init__.py
tool_parse/integrations/langchain.py
tool_parse/marshal.py
tool_parse-1.1.3.dist-info/LICENSE
tool_parse-1.1.3.dist-info/METADATA
tool_parse-1.1.3.dist-info/WHEEL
tool_parse-1.1.3.dist-info/RECORD
