Metadata-Version: 2.1
Name: tool-parse
Version: 1.1.3
Summary: Making LLM Tool-Calling Simpler.
Home-page: https://github.com/synacktraa/tool-parse
License: MIT
Author: Harsh Verma
Author-email: synacktra.work@gmail.com
Requires-Python: >=3.8,<3.13
Classifier: License :: OSI Approved :: MIT License
Classifier: Programming Language :: Python :: 3
Classifier: Programming Language :: Python :: 3.8
Classifier: Programming Language :: Python :: 3.9
Classifier: Programming Language :: Python :: 3.10
Classifier: Programming Language :: Python :: 3.11
Classifier: Programming Language :: Python :: 3.12
Provides-Extra: langchain
Provides-Extra: pydantic
Requires-Dist: docstring-parser (>=0.15)
Requires-Dist: langchain-core (>=0.3.0) ; (python_version >= "3.9") and (extra == "langchain")
Requires-Dist: pydantic (>=2.0) ; extra == "pydantic" or extra == "langchain"
Project-URL: Repository, https://github.com/synacktraa/tool-parse
